scriptcraft/ReadMe.md
scriptcraft/__init__.py
scriptcraft/_version.py
scriptcraft/cli/release_cli.py
scriptcraft/common/README.md
scriptcraft/common/__init__.py
scriptcraft/common/cli/__init__.py
scriptcraft/common/cli/argument_parsers.py
scriptcraft/common/cli/main_runner.py
scriptcraft/common/core/README.md
scriptcraft/common/core/__init__.py
scriptcraft/common/core/base.py
scriptcraft/common/core/config.py
scriptcraft/common/data/__init__.py
scriptcraft/common/data/cleaning.py
scriptcraft/common/data/comparison.py
scriptcraft/common/data/comparison_core.py
scriptcraft/common/data/dataframe.py
scriptcraft/common/data/processing.py
scriptcraft/common/data/processor.py
scriptcraft/common/data/validation.py
scriptcraft/common/io/__init__.py
scriptcraft/common/io/data_loading.py
scriptcraft/common/io/directory_ops.py
scriptcraft/common/io/file_ops.py
scriptcraft/common/io/path_resolver.py
scriptcraft/common/io/paths.py
scriptcraft/common/logging/__init__.py
scriptcraft/common/logging/context.py
scriptcraft/common/logging/core.py
scriptcraft/common/logging/formatters.py
scriptcraft/common/logging/handlers.py
scriptcraft/common/logging/utils.py
scriptcraft/common/pipeline/__init__.py
scriptcraft/common/pipeline/base.py
scriptcraft/common/pipeline/execution.py
scriptcraft/common/pipeline/factory.py
scriptcraft/common/pipeline/utils.py
scriptcraft/common/plugins/README.md
scriptcraft/common/plugins/__init__.py
scriptcraft/common/registry/__init__.py
scriptcraft/common/registry/plugin_registry.py
scriptcraft/common/registry/registry.py
scriptcraft/common/time/__init__.py
scriptcraft/common/time/date_utils.py
scriptcraft/common/time/timepoint.py
scriptcraft/common/tools/__init__.py
scriptcraft/common/tools/expected.py
scriptcraft/common/tools/patterns.py
scriptcraft/common/tools/runner.py
scriptcraft/misc/README.md
scriptcraft/misc/__init__.py
scriptcraft/pipelines/README.md
scriptcraft/pipelines/__init__.py
scriptcraft/pipelines/git_pipelines.py
scriptcraft_python-1.6.3.dist-info/METADATA
scriptcraft_python-1.6.3.dist-info/WHEEL
scriptcraft_python-1.6.3.dist-info/entry_points.txt
scriptcraft_python-1.6.3.dist-info/top_level.txt
scriptcraft_python-1.6.3.dist-info/RECORD
