Metadata-Version: 2.4
Name: scriptcraft-python
Version: 1.6.3
Summary: Data processing and quality control tools for research workflows
Author-email: ScriptCraft Team <scriptcraft@example.com>
Maintainer-email: ScriptCraft Team <scriptcraft@example.com>
Project-URL: Homepage, https://github.com/mcusac/ScriptCraft-Workspace
Project-URL: Documentation, https://github.com/mcusac/ScriptCraft-Workspace#readme
Project-URL: Repository, https://github.com/mcusac/ScriptCraft-Workspace
Project-URL: Issues, https://github.com/mcusac/ScriptCraft-Workspace/issues
Keywords: data-processing,quality-control,research,validation,automation
Classifier: Development Status :: 4 - Beta
Classifier: Intended Audience :: Developers
Classifier: Intended Audience :: Science/Research
Classifier: License :: OSI Approved :: MIT License
Classifier: Operating System :: OS Independent
Classifier: Programming Language :: Python :: 3
Classifier: Programming Language :: Python :: 3.8
Classifier: Programming Language :: Python :: 3.9
Classifier: Programming Language :: Python :: 3.10
Classifier: Programming Language :: Python :: 3.11
Classifier: Programming Language :: Python :: 3.12
Classifier: Topic :: Scientific/Engineering
Classifier: Topic :: Scientific/Engineering :: Information Analysis
Classifier: Topic :: Software Development :: Libraries :: Python Modules
Classifier: Topic :: Utilities
Requires-Python: >=3.8
Requires-Dist: pandas>=1.3.0
Requires-Dist: numpy>=1.21.0
Requires-Dist: openpyxl>=3.0.0
Requires-Dist: xlrd>=2.0.0
Requires-Dist: pyyaml>=6.0
Requires-Dist: click>=8.0.0
Requires-Dist: rich>=12.0.0
Requires-Dist: pydantic>=1.9.0
Requires-Dist: python-dateutil>=2.8.0
Requires-Dist: pytz>=2021.1
Requires-Dist: python-docx>=0.8.11
Requires-Dist: typing-extensions>=4.0.0
Provides-Extra: web
Requires-Dist: selenium>=4.0.0; extra == "web"
Provides-Extra: all
Requires-Dist: selenium>=4.0.0; extra == "all"
Provides-Extra: dev
Requires-Dist: pytest>=7.0.0; extra == "dev"
Requires-Dist: pytest-cov>=4.0.0; extra == "dev"
Requires-Dist: black>=22.0.0; extra == "dev"
Requires-Dist: flake8>=5.0.0; extra == "dev"
Requires-Dist: mypy>=1.0.0; extra == "dev"
Requires-Dist: pre-commit>=2.20.0; extra == "dev"
Provides-Extra: test
Requires-Dist: pytest>=7.0.0; extra == "test"
Requires-Dist: pytest-cov>=4.0.0; extra == "test"
